huaweicloudsdkcloudpond/__init__.py
huaweicloudsdkcloudpond/v1/__init__.py
huaweicloudsdkcloudpond/v1/cloudpond_async_client.py
huaweicloudsdkcloudpond/v1/cloudpond_client.py
huaweicloudsdkcloudpond/v1/model/__init__.py
huaweicloudsdkcloudpond/v1/model/charge_mode.py
huaweicloudsdkcloudpond/v1/model/compute_spec.py
huaweicloudsdkcloudpond/v1/model/condition.py
huaweicloudsdkcloudpond/v1/model/create_edge_site.py
huaweicloudsdkcloudpond/v1/model/create_edge_site_request.py
huaweicloudsdkcloudpond/v1/model/create_edge_site_request_body.py
huaweicloudsdkcloudpond/v1/model/create_edge_site_response.py
huaweicloudsdkcloudpond/v1/model/create_location.py
huaweicloudsdkcloudpond/v1/model/delete_edge_site_request.py
huaweicloudsdkcloudpond/v1/model/delete_edge_site_response.py
huaweicloudsdkcloudpond/v1/model/edge_site_detail.py
huaweicloudsdkcloudpond/v1/model/effect.py
huaweicloudsdkcloudpond/v1/model/list_edge_site_metrics_request.py
huaweicloudsdkcloudpond/v1/model/list_edge_site_metrics_response.py
huaweicloudsdkcloudpond/v1/model/list_edge_sites_request.py
huaweicloudsdkcloudpond/v1/model/list_edge_sites_response.py
huaweicloudsdkcloudpond/v1/model/list_quotas_request.py
huaweicloudsdkcloudpond/v1/model/list_quotas_response.py
huaweicloudsdkcloudpond/v1/model/list_racks_request.py
huaweicloudsdkcloudpond/v1/model/list_racks_response.py
huaweicloudsdkcloudpond/v1/model/list_storage_pools_request.py
huaweicloudsdkcloudpond/v1/model/list_storage_pools_response.py
huaweicloudsdkcloudpond/v1/model/list_supported_regions_request.py
huaweicloudsdkcloudpond/v1/model/list_supported_regions_response.py
huaweicloudsdkcloudpond/v1/model/list_supported_zones_request.py
huaweicloudsdkcloudpond/v1/model/list_supported_zones_response.py
huaweicloudsdkcloudpond/v1/model/location_detail.py
huaweicloudsdkcloudpond/v1/model/market_options.py
huaweicloudsdkcloudpond/v1/model/metric_data_detail.py
huaweicloudsdkcloudpond/v1/model/metric_data_detail_dimension.py
huaweicloudsdkcloudpond-3.1.184.dist-info/METADATA
huaweicloudsdkcloudpond-3.1.184.dist-info/WHEEL
huaweicloudsdkcloudpond-3.1.184.dist-info/licenses/LICENSE
huaweicloudsdkcloudpond-3.1.184.dist-info/RECORD
